mobile_env/__init__.py
mobile_env/core/__init__.py
mobile_env/core/arrival.py
mobile_env/core/base.py
mobile_env/core/channels.py
mobile_env/core/entities.py
mobile_env/core/logging.py
mobile_env/core/metrics.py
mobile_env/core/movement.py
mobile_env/core/schedules.py
mobile_env/core/util.py
mobile_env/core/utilities.py
mobile_env/handlers/__init__.py
mobile_env/handlers/central.py
mobile_env/handlers/handler.py
mobile_env/handlers/multi_agent.py
mobile_env/scenarios/__init__.py
mobile_env/scenarios/large.py
mobile_env/scenarios/medium.py
mobile_env/scenarios/registry.py
mobile_env/scenarios/small.py
mobile_env/wrappers/__init__.py
mobile_env/wrappers/multi_agent.py
tests/__init__.py
tests/test_central_envs.py
tests/test_env_stepping.py
mobile_env-2.0.3.dist-info/LICENSE
mobile_env-2.0.3.dist-info/METADATA
mobile_env-2.0.3.dist-info/WHEEL
mobile_env-2.0.3.dist-info/top_level.txt
mobile_env-2.0.3.dist-info/RECORD
