Metadata-Version: 2.1
Name: mobile-env
Version: 2.0.3
Summary: mobile-env: An Open Environment for Autonomous Coordination in Wireless Mobile Networks
Home-page: https://github.com/stefanbschneider/mobile-env
Author: Stefan Schneider, Stefan Werner
License: MIT
Classifier: Programming Language :: Python :: 3
Classifier: License :: OSI Approved :: MIT License
Classifier: Operating System :: OS Independent
Requires-Python: >=3.9.0
License-File: LICENSE
Requires-Dist: gymnasium <1.0.0
Requires-Dist: matplotlib
Requires-Dist: numpy
Requires-Dist: pandas
Requires-Dist: pygame
Requires-Dist: shapely
Requires-Dist: svgpath2mpl
